omniscient/__init__.py
orv-0.0.1.dist-info/LICENSE
orv-0.0.1.dist-info/METADATA
orv-0.0.1.dist-info/WHEEL
orv-0.0.1.dist-info/top_level.txt
orv-0.0.1.dist-info/RECORD
