Metadata-Version: 2.1
Name: orv
Version: 0.0.1
Summary: orv module
Home-page: https://github.com/pypa/sampleproject
Author: Merxlc
Author-email: liddleconquerer@gmail.com
License: UNKNOWN
Platform: UNKNOWN
Classifier: Programming Language :: Python :: 3
Classifier: License :: OSI Approved :: MIT License
Classifier: Operating System :: OS Independent
Requires-Python: >=3.6
